hi_lasso/__init__.py
hi_lasso/glmnet_model.py
hi_lasso/hi_lasso.py
hi_lasso/util.py
hi_lasso-1.0.6.dist-info/LICENSE
hi_lasso-1.0.6.dist-info/METADATA
hi_lasso-1.0.6.dist-info/WHEEL
hi_lasso-1.0.6.dist-info/top_level.txt
hi_lasso-1.0.6.dist-info/RECORD
