Metadata-Version: 2.1
Name: hi-lasso
Version: 1.0.6
Summary: High-Demensional LASSO
Home-page: https://github.com/datax-lab/Hi-LASSO
Author: Jongkwon Jo
Author-email: jongkwon.jo@gmail.com
License: UNKNOWN
Platform: UNKNOWN
Classifier: Programming Language :: Python :: 3
Classifier: License :: OSI Approved :: MIT License
Classifier: Operating System :: OS Independent
Requires-Python: >=3.6
License-File: LICENSE
Requires-Dist: glmnet
Requires-Dist: tqdm
